{
    "countryCode": "ba",
    "country": "Bosnia & Herzegovina",
    "partyName": {
        "en": "Pirate Party Bosnia and Herzegovina",
        "ba": "Piratska Partija Bosne i Hercegovine"
    },
    "type": "national",
    "websites": {
        "official": "http://www.piratskapartija.ba"
    },
    "socialNetworks": {
        "facebook": {
            "username": "PiratskaPartija.ba",
            "id": "341947585847984"
        },
        "twitter": {
            "username": "PP_ba",
            "hashtag": null
        },
        "youtube": "piratskapartijaBA",
        "dfsn": {
            "id": "piratskapartija@joindiaspora.com",
            "type": "diaspora"
        }
    },
    "membership": {
        "ppi": false,
        "ppeu": false
    },
    "contact": {
        "general": "info@piratskapartija.ba"
    },
    "partyCode": "PPBA",
    "defunct": true
}
